stellar_data_api_client/__init__.py
stellar_data_api_client/api/__init__.py
stellar_data_api_client/api/default/__init__.py
stellar_data_api_client/api/default/get_cn_futures_daily_history.py
stellar_data_api_client/client.py
stellar_data_api_client/models/__init__.py
stellar_data_api_client/models/http_validation_error.py
stellar_data_api_client/models/validation_error.py
stellar_data_api_client/py.typed
stellar_data_api_client/types.py
stellar_data_api_client-0.1.0.dist-info/WHEEL
stellar_data_api_client-0.1.0.dist-info/METADATA
stellar_data_api_client-0.1.0.dist-info/RECORD
