Metadata-Version: 2.1
Name: stellar-data-api-client
Version: 0.1.0
Summary: A client library for accessing Stellar Data API
Requires-Python: >=3.7,<4.0
Classifier: Programming Language :: Python :: 3
Classifier: Programming Language :: Python :: 3.7
Classifier: Programming Language :: Python :: 3.8
Classifier: Programming Language :: Python :: 3.9
Classifier: Programming Language :: Python :: 3.10
Requires-Dist: attrs (>=21.3.0)
Requires-Dist: httpx (>=0.15.4,<0.24.0)
Requires-Dist: python-dateutil (>=2.8.0,<3.0.0)
